{
  "001": {
    "codigo": "001",
    "nombre": "Casa de Maduro",
    "direccion": "123",
    "ciudad": "Miami",
    "barrio": "000",
    "codigoAsesorResponsable": "1020302622",
    "tipoInmueble": "APARTAMENTO",
    "finalidad": "ARRIENDO",
    "precio": 3000.0,
    "area": 10.0,
    "numeroHabitaciones": 1,
    "numeroBanos": 1,
    "estadoInmueble": "USADO",
    "disponibilidad": "RESERVADO",
    "fotoPortada": "/uploads/inmuebles/portada_d6b1f382-c070-4e36-9ca4-5ab376507764.webp",
    "fotosGaleria": []
  },
  "321": {
    "codigo": "321",
    "nombre": "Casa Sevilla",
    "direccion": "calle 60 #48-20",
    "ciudad": "Sevilla",
    "barrio": "Obrero",
    "codigoAsesorResponsable": "1020302622",
    "tipoInmueble": "CASA",
    "finalidad": "ARRIENDO",
    "precio": 500.0,
    "area": 90.0,
    "numeroHabitaciones": 5,
    "numeroBanos": 2,
    "estadoInmueble": "USADO",
    "disponibilidad": "DISPONIBLE",
    "fotoPortada": "/uploads/inmuebles/portada_3d3f45ad-837f-4ebc-a931-b5b8f2b03c4f.png",
    "fotosGaleria": []
  },
  "444": {
    "codigo": "444",
    "nombre": "Luis",
    "direccion": "calle 15 Norte #14-99",
    "ciudad": "Sevilla",
    "barrio": "La fogata",
    "codigoAsesorResponsable": "1020302622",
    "tipoInmueble": "LOCAL_COMERCIAL",
    "finalidad": "VENTA",
    "precio": 500.0,
    "area": 345.0,
    "numeroHabitaciones": 4,
    "numeroBanos": 2,
    "estadoInmueble": "NUEVO",
    "disponibilidad": "RESERVADO",
    "fotoPortada": "/uploads/inmuebles/portada_6582a9a4-c7d7-4d81-803e-6f84c1db9cc3.jpg",
    "fotosGaleria": []
  },
  "567": {
    "codigo": "567",
    "nombre": "Casa de Netanyahu",
    "direccion": "000",
    "ciudad": "Tel Aviv",
    "barrio": "000",
    "codigoAsesorResponsable": "1020302622",
    "tipoInmueble": "CASA",
    "finalidad": "VENTA",
    "precio": 500000.0,
    "area": 150.0,
    "numeroHabitaciones": 7,
    "numeroBanos": 3,
    "estadoInmueble": "USADO",
    "disponibilidad": "NO_DISPONIBLE",
    "fotoPortada": "/uploads/inmuebles/portada_ae7afaf3-f044-415c-af8b-1c2d9e4de755.jpg",
    "fotosGaleria": []
  },
  "7698": {
    "codigo": "7698",
    "nombre": "ggani",
    "direccion": "calle 60 #48-20",
    "ciudad": "Tel Aviv",
    "barrio": "Obrero",
    "codigoAsesorResponsable": "1020302622",
    "tipoInmueble": "APARTAMENTO",
    "finalidad": "ARRIENDO",
    "precio": 500.0,
    "area": 78.0,
    "numeroHabitaciones": 4,
    "numeroBanos": 2,
    "estadoInmueble": "NUEVO",
    "disponibilidad": "NO_DISPONIBLE",
    "fotoPortada": "/uploads/inmuebles/portada_765e4591-3f0a-4683-ab69-86d4f6260977.webp",
    "fotosGaleria": []
  },
  "11100": {
    "codigo": "11100",
    "nombre": "Prueba de imagenes",
    "direccion": "calle 15 Norte #14-99",
    "ciudad": "Tel Aviv",
    "barrio": "Obrero",
    "codigoAsesorResponsable": "1020302622",
    "tipoInmueble": "LOCAL_COMERCIAL",
    "finalidad": "ARRIENDO",
    "precio": 3000.0,
    "area": 10.0,
    "numeroHabitaciones": 1,
    "numeroBanos": 1,
    "estadoInmueble": "EN_REMODELACION",
    "disponibilidad": "DISPONIBLE",
    "fotoPortada": "/uploads/inmuebles/portada_3471952d-1cf4-449f-9556-a5f8e904763b.jpg",
    "fotosGaleria": []
  },
  "989": {
    "codigo": "989",
    "nombre": "Casa Sevilla",
    "direccion": "calle 60 #48-20",
    "ciudad": "Sevilla",
    "barrio": "Obrero",
    "codigoAsesorResponsable": "1020302622",
    "tipoInmueble": "CASA",
    "finalidad": "ARRIENDO",
    "precio": 500000.0,
    "area": 90.0,
    "numeroHabitaciones": 5,
    "numeroBanos": 2,
    "estadoInmueble": "USADO",
    "disponibilidad": "NO_DISPONIBLE",
    "fotoPortada": "/uploads/inmuebles/portada_bd839620-543d-457e-b722-38eaa32de7a3.jpg",
    "fotosGaleria": []
  },
  "6789": {
    "codigo": "6789",
    "nombre": "Casa Albert Epstein",
    "direccion": "calle 60 #48-20",
    "ciudad": "Tel Aviv",
    "barrio": "Obrero",
    "codigoAsesorResponsable": "1020302622",
    "tipoInmueble": "CASA",
    "finalidad": "ARRIENDO",
    "precio": 500.0,
    "area": 60.0,
    "numeroHabitaciones": 5,
    "numeroBanos": 2,
    "estadoInmueble": "NUEVO",
    "disponibilidad": "DISPONIBLE",
    "fotoPortada": "/uploads/inmuebles/portada_7524f9b0-3a54-4c4a-8fc2-711be217843b.jpg",
    "fotosGaleria": []
  }
}